drf_crud_proxy/__init__.py
drf_crud_proxy/apps.py
drf_crud_proxy/generics.py
drf_crud_proxy/mixins.py
drf_crud_proxy/proxy.py
drf_crud_proxy/viewsets.py
drf_crud_proxy-0.5.0.dist-info/LICENSE
drf_crud_proxy-0.5.0.dist-info/METADATA
drf_crud_proxy-0.5.0.dist-info/WHEEL
drf_crud_proxy-0.5.0.dist-info/top_level.txt
drf_crud_proxy-0.5.0.dist-info/RECORD
