Metadata-Version: 2.1
Name: drf-crud-proxy
Version: 0.5.0
Summary: Separate serializers for parsing requests and returning responses in DRF
Home-page: https://github.com/attevaltojarvi/drf-crud-proxy
Author: attevaltojarvi
Author-email: atte.valtojarvi@gmail.com
License: MIT
Keywords: Django REST Framework,Serializers,REST,API,Django
Classifier: Development Status :: 3 - Alpha
Classifier: Framework :: Django
Classifier: Framework :: Django :: 4.2
Classifier: Framework :: Django :: 5.0
Classifier: Framework :: Django :: 5.1
Classifier: Intended Audience :: Developers
Classifier: License :: OSI Approved :: MIT License
Classifier: Natural Language :: Finnish
Classifier: Programming Language :: Python
Classifier: Programming Language :: Python :: 3.8
Classifier: Programming Language :: Python :: 3.9
Classifier: Programming Language :: Python :: 3.10
Classifier: Programming Language :: Python :: 3.11
Classifier: Programming Language :: Python :: 3.12
License-File: LICENSE
Requires-Dist: Django <5.2,>=4.2
Requires-Dist: djangorestframework >=3.8
